nonebot_plugin_antirecall/LICENSE
nonebot_plugin_antirecall/__init__.py
nonebot_plugin_antirecall/poetry.lock
nonebot_plugin_antirecall/pyproject.toml
nonebot_plugin_antirecall-0.1.4.dist-info/LICENSE
nonebot_plugin_antirecall-0.1.4.dist-info/WHEEL
nonebot_plugin_antirecall-0.1.4.dist-info/METADATA
nonebot_plugin_antirecall-0.1.4.dist-info/RECORD
