Metadata-Version: 2.1
Name: nonebot-plugin-antirecall
Version: 0.1.4
Summary: Anti-recall plugin for QQbot in Nonebot2
Home-page: https://github.com/Jerry080801/nonebot-plugin-antirecall
License: MIT
Author: Jerry
Author-email: jerry080801@icloud.com
Requires-Python: >=3.7.3,<4.0.0
Classifier: License :: OSI Approved :: MIT License
Classifier: Programming Language :: Python :: 3
Classifier: Programming Language :: Python :: 3.10
Classifier: Programming Language :: Python :: 3.8
Classifier: Programming Language :: Python :: 3.9
Requires-Dist: nonebot-adapter-onebot (>=2.0.0-beta.1,<3.0.0)
Requires-Dist: nonebot2 (>=2.0.0-beta.4,<3.0.0)
Project-URL: Repository, https://github.com/Jerry080801/nonebot-plugin-antirecall
